pytest_relaxed/__init__.py
pytest_relaxed/_version.py
pytest_relaxed/classes.py
pytest_relaxed/fixtures.py
pytest_relaxed/plugin.py
pytest_relaxed/raises.py
pytest_relaxed/reporter.py
pytest_relaxed/trap.py
pytest_relaxed-2.0.2.dist-info/LICENSE
pytest_relaxed-2.0.2.dist-info/METADATA
pytest_relaxed-2.0.2.dist-info/WHEEL
pytest_relaxed-2.0.2.dist-info/entry_points.txt
pytest_relaxed-2.0.2.dist-info/top_level.txt
pytest_relaxed-2.0.2.dist-info/RECORD
