Metadata-Version: 2.1
Name: pytest-relaxed
Version: 2.0.2
Summary: Relaxed test discovery/organization for pytest
Home-page: https://pytest-relaxed.readthedocs.io/
Author: Jeff Forcier
Author-email: jeff@bitprophet.org
License: BSD
Project-URL: Source, https://github.com/bitprophet/pytest-relaxed
Project-URL: Changelog, https://github.com/bitprophet/pytest-relaxed/blob/main/docs/changelog.rst
Project-URL: CI, https://app.circleci.com/pipelines/github/bitprophet/pytest-relaxed
Platform: UNKNOWN
Classifier: Development Status :: 5 - Production/Stable
Classifier: Framework :: Pytest
Classifier: Intended Audience :: Developers
Classifier: License :: OSI Approved :: BSD License
Classifier: Operating System :: OS Independent
Classifier: Programming Language :: Python
Classifier: Programming Language :: Python :: 3
Classifier: Programming Language :: Python :: 3 :: Only
Classifier: Programming Language :: Python :: 3.6
Classifier: Programming Language :: Python :: 3.7
Classifier: Programming Language :: Python :: 3.8
Classifier: Programming Language :: Python :: 3.9
Classifier: Programming Language :: Python :: 3.10
Classifier: Programming Language :: Python :: 3.11
Classifier: Topic :: Software Development :: Testing
Requires-Python: >=3.6
Requires-Dist: pytest >=7
Requires-Dist: decorator
